morpheus_data_api/__init__.py
morpheus_data_api/mock.py
morpheus_data_api-0.0.2.dist-info/LICENSE
morpheus_data_api-0.0.2.dist-info/METADATA
morpheus_data_api-0.0.2.dist-info/WHEEL
morpheus_data_api-0.0.2.dist-info/entry_points.txt
morpheus_data_api-0.0.2.dist-info/top_level.txt
morpheus_data_api-0.0.2.dist-info/RECORD
