Metadata-Version: 2.1
Name: morpheus-data-api
Version: 0.0.2
Summary: Morpheus Data API Client
Home-page: https://github.com/Accenture/morpheus-data-api/
Author: Roger Foskett
Author-email: r_foskett@hotmail.com
License: Apache License 2.0
Platform: UNKNOWN
Classifier: Programming Language :: Python :: 3
Classifier: License :: OSI Approved :: Apache Software License
Classifier: Operating System :: OS Independent
Requires-Dist: jmespath (==0.10.0)
Requires-Dist: pyyaml (==5.4.1)
Requires-Dist: requests (==2.25.1)
Requires-Dist: responses (==0.13.3)
